detaillogger/__init__.py
detaillogger/core.py
detaillogger/detail_logger.py
detaillogger-0.2.0.dist-info/METADATA
detaillogger-0.2.0.dist-info/WHEEL
detaillogger-0.2.0.dist-info/entry_points.txt
detaillogger-0.2.0.dist-info/RECORD
