Metadata-Version: 2.4
Name: detaillogger
Version: 0.2.0
Summary: DetailLogger is a lightweight Python utility for enhanced logging and exception data tracing.
Project-URL: Homepage, https://github.com/rlapine/DetailLogger
Project-URL: Repository, https://github.com/rlapine/DetailLogger
Project-URL: Documentation, https://github.com/rlapine/DetailLogger/README.md
Author-email: Ryan LaPine <github.stunt845@passinbox.com>
Maintainer-email: Ryan LaPine <github.stunt845@passinbox.com>
License: MIT
Keywords: CLI tools,Python logging,console output,custom logger,debugging,developer tools,diagnostics,log formatting,log levels,logger,logging,structured logging,terminal output,trace logs,verbose logging
Classifier: Intended Audience :: Developers
Classifier: License :: OSI Approved :: MIT License
Classifier: Operating System :: OS Independent
Classifier: Programming Language :: Python :: 3
Classifier: Topic :: Software Development :: Libraries
Classifier: Topic :: Utilities
Requires-Python: >=3.8
